fileindexer/__init__.py
fileindexer/__main__.py
fileindexer-1.0.2.dist-info/LICENSE
fileindexer-1.0.2.dist-info/METADATA
fileindexer-1.0.2.dist-info/WHEEL
fileindexer-1.0.2.dist-info/entry_points.txt
fileindexer-1.0.2.dist-info/top_level.txt
fileindexer-1.0.2.dist-info/RECORD
