Metadata-Version: 2.1
Name: fileindexer
Version: 1.0.2
Summary: Script for indexing text files using line offsets.
Home-page: https://github.com/mdocekal/fileindexer
Author: Martin Dočekal
Keywords: indexing,text files
Requires-Python: >=3.6
License-File: LICENSE
Requires-Dist: tqdm (>=4.62.3)
